{
  "document": "sf2e-playercore-PZO22001-HC-Player-Core-000",
  "chunks": [
    {
      "id": "coalesced-/page/0/Text/5",
      "block_type": "Coalesced",
      "text": "PZ022001-HC Printed\n\nPrinted in China.",
      "page": 0,
      "bbox": [
        441.0,
        751.5,
        546.64453125,
        761.49755859375
      ],
      "section_hierarchy": {},
      "content_kind": "narrative",
      "is_rule_bearing": false,
      "tags": [],
      "traits": [],
      "spell_rank": null,
      "traditions": [],
      "spell_stats": {},
      "section_path": []
    }
  ]
}