{
  "ruleset_id": "sf2e-playercore",
  "doc_signature": "4e0a4e6cb9d37afebe090427c87fc0125640c6ac0e412c06f8abb837378200a1",
  "version": "v20",
  "source_fingerprint": "1a96648f463f4ff13db015d6ba7e1b6deaa9c489135ef7a8cd18bee4ae4d3c76",
  "schema_version": "1.0",
  "deterministic_rules": {},
  "nondeterministic_flags": [
    "general",
    "skill",
    "feat",
    "chapter",
    "sectionheader",
    "text",
    "table",
    "tablecell"
  ],
  "drift_criteria": {
    "heading_hierarchy": [
      "CHAPTER 5: FEATS",
      "**GENERAL FEATS**",
      "**GENERAL SKILL FEATS**",
      "PLAYER CORE",
      "PLAYER CORE",
      "**ADDITIONAL LORE FEAT 1**",
      "**GENERAL** **SKILL**",
      "**ADOPTED ANCESTRY FEAT 1**",
      "**GENERAL**",
      "**ADVANCED FIRST AID** **FEAT 7**",
      "**AKASHIC SYNC **[one-action] **FEAT 7**",
      "**AKASHIC TRANSCENDENCE** **FEAT 15**",
      "**ANCESTRAL PARAGON FEAT 3**",
      "**ARMOR PROFICIENCY FEAT 1**",
      "**ASSURANCE FEAT 1**",
      "**AUGMENTED BODY** **FEAT 1**",
      "**AUTOMATIC KNOWLEDGE** **FEAT 2**",
      "**BARGAIN HUNTER** **FEAT 1**",
      "**BARRICADE **[one-action] **FEAT 1**",
      "**BATTLE CRY** **FEAT 7**",
      "**BATTLE MEDICINE **[one-action] **FEAT 1**",
      "**CONTINUAL RECOVERY** **FEAT 2**",
      "**DUBIOUS KNOWLEDGE** **FEAT 1**",
      "**ELECTRICAL ENGINEER** **FEAT 1**",
      "**EXPEDITIOUS SEARCH** **FEAT 7**",
      "**EXPERIENCED PROFESSIONAL** **FEAT 1**",
      "**EXPERIENCED SMUGGLER** **FEAT 1**",
      "**EXPERIENCED TRACKER** **FEAT 1**",
      "**EXPRESS DRIVER** **FEAT 1**",
      "**FACE IN THE CROWD** **FEAT 1**",
      "**FASCINATING PERFORMANCE** **FEAT 1**",
      "**FAST RECOVERY** **FEAT 1**",
      "**FAVORED DISGUISE** **FEAT 1**",
      "**FEATHER STEP** **FEAT 1**",
      "**FEIGN DEATH **[REACTION] **FEAT 2**",
      "**Trigger** You take damage.",
      "**FOOL THE CAMERA** **FEAT 7**",
      "**GROUP COERCION** **FEAT 1**",
      "**GROUP IMPRESSION** **FEAT 1**",
      "**HEFTY HAULER** **FEAT 1**",
      "**HOLOGRAM SKEPTIC** **FEAT 1**",
      "**IMPECCABLE CRAFTING** **FEAT 7**",
      "**IMPRESSIVE PERFORMANCE** **FEAT 1**",
      "**INCREDIBLE INITIATIVE** **FEAT 1**",
      "**INTIMIDATING GLARE** **FEAT 1**",
      "**INTIMIDATING PROWESS** **FEAT 2**",
      "**INTIMIDATING SHOT **[ONE-ACTION] **FEAT 1**",
      "**INVENTOR** **FEAT 2**",
      "**JUST KIDDING **[reaction] **FEAT 1**",
      "**KIP UP **[free-action] **FEAT 7**",
      "**KISS IT BETTER **[ONE-ACTION] **FEAT 2**",
      "PLAYER CORE",
      "**LASTING COERCION** **FEAT 2**",
      "**LEGENDARY CODEBREAKER** **FEAT 15**",
      "**LEGENDARY LINGUIST** **FEAT 15**",
      "**LEGENDARY MEDIC** **FEAT 15**",
      "**LEGENDARY NEGOTIATION **[three-actions] **FEAT 15**",
      "**LEGENDARY PERFORMER** **FEAT 15**",
      "**LEGENDARY PROFESSIONAL** **FEAT 15**",
      "**LEGENDARY SNEAK** **FEAT 15**",
      "**LEGENDARY SURVIVALIST** **FEAT 15**",
      "**LEGENDARY THIEF** **FEAT 15**",
      "**LEGENDARY TROLL **[one-action] **FEAT 15**",
      "**LENGTHY DIVERSION** **FEAT 1**",
      "**MAGICAL CRAFTING** **FEAT 2**",
      "**MANAGEMENT MATERIAL** **FEAT 1**",
      "**MONSTER CRAFTING** **FEAT 7**",
      "**MULTILINGUAL** **FEAT 1**",
      "**NIMBLE CRAWL** **FEAT 2**",
      "**NO CAUSE FOR ALARM **[three-actions] **FEAT 1**",
      "**ODDITY IDENTIFICATION** **FEAT 1**",
      "**PERCUSSIVE MAINTENANCE **[one-action] **FEAT 2**",
      "**PHISHING EXPERTISE** **FEAT 1**",
      "**PRESCIENT CONSUMABLE** **FEAT 7**",
      "**PRESCIENT PLANNER** **FEAT 3**",
      "**QUICK COERCION** **FEAT 1**",
      "**QUICK DISGUISE** **FEAT 2**",
      "**QUICK IDENTIFICATION** **FEAT 1**",
      "**QUICK RECOGNITION** **FEAT 7**",
      "**QUICK REPAIR** **FEAT 1**",
      "**QUICK SQUEEZE** **FEAT 1**",
      "**QUICK SWIM** **FEAT 7**",
      "**QUICK UNLOCK** **FEAT 7**",
      "**QUIET ALLIES** **FEAT 2**",
      "**RAPID MANTEL** **FEAT 2**",
      "**READ LIPS** **FEAT 1**",
      "**RECOGNIZE SPELL **[reaction] **FEAT 1**",
      "**GENERAL** **SECRET** **SKILL**",
      "**RELIGIOUS TALISMAN** **FEAT 7**",
      "**GENERAL** **SKILL**",
      "**GENERAL**",
      "**ROBUST RECOVERY** **FEAT 2**",
      "**Prerequisites** expert in Medicine",
      "**SCARE TO DEATH **[one-action] **FEAT 15**",
      "**SCHOOLED IN SECRETS** **FEAT 1**",
      "**SEASONED** **FEAT 1**",
      "**SERUM CRAFTING** **FEAT 1**",
      "**SHAMELESS REQUEST** **FEAT 7**",
      "**STUDENT OF THE CANON** **FEAT 1**",
      "**STUNT MANEUVER** **FEAT 2**",
      "**SUBTLE THEFT** **FEAT 1**",
      "**SURVEY WILDLIFE FEAT 1**",
      "**SWIFT SNEAK** **FEAT 7**",
      "**TAKE THE WHEEL **[one-action] **FEAT 3**",
      "**TECH CRAFTING** **FEAT 2**",
      "**TERRAIN EXPERTISE** **FEAT 1**",
      "**TERRAIN STALKER** **FEAT 1**",
      "**TERRIFIED RETREAT** **FEAT 7**",
      "**TITAN WRESTLER** **FEAT 1**",
      "**TOUGHNESS** **FEAT 1**",
      "**TRAIN ANIMAL** **FEAT 1**",
      "**TRICK MAGIC ITEM **[one-action] **FEAT 1**",
      "**UNIFIED THEORY** **FEAT 15**",
      "**UNMISTAKABLE LORE** **FEAT 2**",
      "**UNTRAINED IMPROVISATION** **FEAT 3**",
      "**UNUSUAL TREATMENT** **FEAT 2**",
      "**URBAN SURVIVALIST** **FEAT 1**",
      "**VIRTUOSIC PERFORMER** **FEAT 1**",
      "**WEAPON PROFICIENCY** **FEAT 1**"
    ],
    "block_type_distribution": {
      "Page": 22,
      "SectionHeader": 119,
      "Text": 828,
      "Table": 11,
      "TableCell": 792
    }
  },
  "created_at": "2026-01-23T05:48:17.339678Z",
  "updated_at": "2026-01-23T05:48:17.339680Z"
}