{
  "ruleset_id": "sf2e-playercore",
  "doc_signature": "15d6ff5f156ec24343371eeaa43662adf77e352238e0b48c83748127ae554cf8",
  "version": "v24",
  "source_fingerprint": "68552453bb1157ed431259eb022be7dca971330367aa4ecff0dfcacadbdd1598",
  "schema_version": "1.0",
  "deterministic_rules": {},
  "nondeterministic_flags": [
    "magic items",
    "investing magic items",
    "activating items",
    "augmentations",
    "biotech",
    "cybernetics",
    "magitech"
  ],
  "drift_criteria": {
    "heading_hierarchy": [
      "MAGIC ITEMS",
      "INVESTING MAGIC ITEMS",
      "**INVEST AN ITEM**",
      "ACTIVATING ITEMS",
      "ACTIVATING INVESTED ITEMS",
      "MANIPULATE ACTIVATIONS",
      "LIMITED ACTIVATIONS",
      "CAST A SPELL",
      "SPECIFIC MAGIC ITEMS",
      "**Type **guiding; **Level **15; **Price **61,000 credits",
      "**Type **life-giving; **Level **7; **Price **3,500 credits",
      "**Type **navigating; **Level **16; **Price **95,000 credits",
      "**Type **projecting; **Level **13; **Price **22,000 credits",
      "**Type **uplifting; **Level **5; **Price **1,600 credits",
      "**AKASHIC LENS** **ITEM 3+**",
      "**ANTIGRAV HARNESS** **ITEM 6+**",
      "**DIVA'S MICROPHONE** **ITEM 4+**",
      "**ITEM TRAITS**",
      "**DUO-ENHANCERS** **ITEM 3**",
      "**HARDLIGHT HANDWRAPS** **ITEM 2+**",
      "**NULL SPACE CHAMBER** **ITEM 4+**",
      "6 PLAYER CORE",
      "**PAIN JOURNAL** **ITEM 7+**",
      "**PROGRAMMER'S PLUSHIE** **ITEM 3+**",
      "**REUSABLE GRENADE SHELL** **ITEM 1**",
      "**SPELL AMPOULE** **ITEM 1+**",
      "**CONSUMABLE** **MAGICAL**",
      "**Usage** held in 1 hand; **Bulk **L",
      "**SPELL CHIP** **ITEM 1+**",
      "**MAGICAL** **TECH**",
      "**Usage** installed in computer or comm unit; **Bulk **\u2013",
      "**SPELL GEM** **ITEM 1+**",
      "**CONSUMABLE** **MAGICAL**",
      "**Usage** held in 1 hand; **Bulk **L",
      "**MAGIC ITEMS**",
      "6 PLAYER CORE",
      "AUGMENTATIONS",
      "IMPLANTATION",
      "Implant Limit",
      "REMOVING AUGMENTATIONS",
      "ACTIVATING AUGMENTATIONS",
      "BIOTECH",
      "**DRAGON GLAND** **AUGMENTATION 1+**",
      "**BIOTECH**",
      "**GILL SHEATH** **AUGMENTATION 1**",
      "**BIOTECH**",
      "**Price **200 credits",
      "**PHOTOSYNTHETIC SKIN** **AUGMENTATION 2**",
      "**ULTRALIGHT WINGS** **AUGMENTATION 3+**",
      "**WILDWISE GRAFT** **AUGMENTATION 2**",
      "CYBERNETICS",
      "**AUTORECOGNITION LENS** **AUGMENTATION 0**",
      "**CARDIAC ACCELERATOR** **AUGMENTATION 5**",
      "**DARKVISION CAPACITORS** **AUGMENTATION 3+**",
      "**DATAJACK** **AUGMENTATION 1+**",
      "**HEARING AID** **AUGMENTATION 0**",
      "**NANO-OPTICS NODE** **AUGMENTATION 11**",
      "**RETINAL REFLECTORS** **AUGMENTATION 1**",
      "**SPEED SUSPENSION** **AUGMENTATION 4+**",
      "**VOCAL MODULATOR** **AUGMENTATION 1**",
      "**VOICE AMPLIFIER** **AUGMENTATION 3**",
      "MAGITECH",
      "**CLOAKING SKIN** **AUGMENTATION 8+**",
      "**PSYCHOACTIVE EYES** **AUGMENTATION 3+**",
      "**REGENERATIVE RUNE SPLICE** **AUGMENTATION 9**",
      "APEX AUGMENTATIONS",
      "**ARTIFICIAL IMMORTALIZER** **AUGMENTATION 17**",
      "**COGNITION ACCELERATOR** **AUGMENTATION 17**",
      "**COSMIC CONNECTOR** **AUGMENTATION 17**",
      "**HYPERNERVES** **AUGMENTATION 17**",
      "**MUSCLE INVIGORATOR** **AUGMENTATION 17**",
      "**PRESENCE INTENSIFIER** **AUGMENTATION 17**",
      "**BIOTECH**",
      "**CYBERNETICS**",
      "**MAGITECH**",
      "**APEX AUGMENTATIONS**"
    ],
    "block_type_distribution": {
      "Page": 12,
      "SectionHeader": 76,
      "Text": 471,
      "Table": 8,
      "TableCell": 547
    }
  },
  "created_at": "2026-01-23T05:59:24.526952Z",
  "updated_at": "2026-01-23T05:59:24.526955Z"
}